<?xml version="1.0" encoding="utf-8"?>
<odoo>
    <!-- Dashboard Kanban View -->
    <record id="view_ariza_dashboard_kanban" model="ir.ui.view">
        <field name="name">ariza.dashboard.kanban</field>
        <field name="model">ariza.kayit</field>
        <field name="arch" type="xml">
            <kanban class="o_kanban_dashboard" create="0">
                <field name="acik_ariza_sayisi"/>
                <field name="tamamlanan_ariza_sayisi"/>
                <field name="iptal_ariza_sayisi"/>
                <field name="toplam_ariza_sayisi"/>
                <templates>
                    <t t-name="kanban-box">
                        <div class="oe_kanban_global_click">
                            <div class="row">
                                <div class="col-6 col-lg-3">
                                    <div class="card">
                                        <div class="card-body text-center">
                                            <h2 class="mb-0">
                                                <field name="acik_ariza_sayisi"/>
                                            </h2>
                                            <p class="text-muted">Açık Arıza</p>
                                        </div>
                                    </div>
                                </div>
                                <div class="col-6 col-lg-3">
                                    <div class="card">
                                        <div class="card-body text-center">
                                            <h2 class="mb-0">
                                                <field name="tamamlanan_ariza_sayisi"/>
                                            </h2>
                                            <p class="text-muted">Tamamlanan</p>
                                        </div>
                                    </div>
                                </div>
                                <div class="col-6 col-lg-3">
                                    <div class="card">
                                        <div class="card-body text-center">
                                            <h2 class="mb-0">
                                                <field name="iptal_ariza_sayisi"/>
                                            </h2>
                                            <p class="text-muted">İptal</p>
                                        </div>
                                    </div>
                                </div>
                                <div class="col-6 col-lg-3">
                                    <div class="card">
                                        <div class="card-body text-center">
                                            <h2 class="mb-0">
                                                <field name="toplam_ariza_sayisi"/>
                                            </h2>
                                            <p class="text-muted">Toplam</p>
                                        </div>
                                    </div>
                                </div>
                            </div>
                        </div>
                    </t>
                </templates>
            </kanban>
        </field>
    </record>

    <!-- Dashboard Action -->
    <record id="action_ariza_dashboard" model="ir.actions.act_window">
        <field name="name">Dashboard</field>
        <field name="res_model">ariza.kayit</field>
        <field name="view_mode">kanban</field>
        <field name="view_id" ref="view_ariza_dashboard_kanban"/>
        <field name="help" type="html">
            <p class="o_view_nocontent_smiling_face">
                Henüz arıza kaydı yok
            </p>
        </field>
    </record>

    <!-- Dashboard Menüsü -->
    <menuitem id="menu_ariza_dashboard"
              name="Dashboard"
              parent="menu_ariza_root"
              action="action_ariza_dashboard"
              sequence="1"/>
</odoo> 